{
    "it": {
        "titolo": "Sestiere di Cannaregio",
        "sottotitolo1": "Ti diamo il bevenuto nel sestiere più esteso di Venezia, ed anche il più popolato."
    },
    "en": {
        "titolo": "Cannaregio District",
        "sottotitolo1": "We welcome you to the largest district of Venice, and also the most populated."
    },
    "de": {
        "titolo": "Sestiere Cannaregio",
        "sottotitolo1": "Wir heißen Sie im größten und bevölkerungsreichsten Stadtteil Venedigs willkommen."
    },
    "es": {
        "titolo": "Distrito de Cannaregio",
        "sottotitolo1": "Te damos la bienvenida al distrito más extenso de Venecia, y también el más poblado."
    },
    "fr": {
        "titolo": "Sestiere Cannaregio",
        "sottotitolo1": "Nous vous souhaitons la bienvenue dans le sestier le plus étendu de Venise, et aussi le plus peuplé."
    }
}
